odoo/addons/field_vector/README.rst
odoo/addons/field_vector/__init__.py
odoo/addons/field_vector/__manifest__.py
odoo/addons/field_vector/fields.py
odoo/addons/field_vector/hooks.py
odoo/addons/field_vector/register.py
odoo/addons/field_vector/i18n/field_vector.pot
odoo/addons/field_vector/i18n/it.po
odoo/addons/field_vector/models/__init__.py
odoo/addons/field_vector/models/ir_model_fields.py
odoo/addons/field_vector/readme/CONTEXT.md
odoo/addons/field_vector/readme/CONTRIBUTORS.md
odoo/addons/field_vector/readme/CREDITS.md
odoo/addons/field_vector/readme/DESCRIPTION.md
odoo/addons/field_vector/readme/INSTALL.md
odoo/addons/field_vector/readme/ROADMAP.md
odoo/addons/field_vector/readme/USAGE.md
odoo/addons/field_vector/static/description/icon.png
odoo/addons/field_vector/static/description/index.html
odoo/addons/field_vector/tests/__init__.py
odoo/addons/field_vector/tests/models.py
odoo/addons/field_vector/tests/test_field_vector.py
odoo_addon_field_vector-19.0.1.0.0.5.dist-info/METADATA
odoo_addon_field_vector-19.0.1.0.0.5.dist-info/WHEEL
odoo_addon_field_vector-19.0.1.0.0.5.dist-info/top_level.txt
odoo_addon_field_vector-19.0.1.0.0.5.dist-info/RECORD
