Metadata-Version: 2.1
Name: odoo-addon-field_vector
Version: 19.0.1.0.0.5
Requires-Dist: numpy
Requires-Dist: odoo==19.0.*
Summary: New specialized field to store vector data
Home-page: https://github.com/OCA/server-tools
License: LGPL-3
Author: ACSONE SA/NV,Odoo Community Association (OCA)
Author-email: support@odoo-community.org
Classifier: Programming Language :: Python
Classifier: Framework :: Odoo
Classifier: Framework :: Odoo :: 19.0
Classifier: License :: OSI Approved :: GNU Lesser General Public License v3 (LGPLv3)
